<?xml version="1.0" encoding="utf-8"?>
<Defs>
  <PawnKindDef Abstract="True" Name="BasePlayerFrogPersonPawnKind">
    <race>Alien_FrogPerson</race>
    <backstoryCategories>
      <li>FrogPersonBackstory</li>
	  <li>InsectRelated</li>
    </backstoryCategories>
    <!-- <baseRecruitDifficulty>0.5</baseRecruitDifficulty> -->
    <isFighter>false</isFighter>
    <apparelIgnoreSeasons>false</apparelIgnoreSeasons>
    <forceNormalGearQuality>true</forceNormalGearQuality>
  </PawnKindDef>
  
  <PawnKindDef ParentName="BasePlayerFrogPersonPawnKind">
    <defName>PlayerFrogPerson</defName>
    <label>frogman</label>
    <combatPower>50</combatPower>
    <defaultFactionType>PlayerColony</defaultFactionType>
    <chemicalAddictionChance>0.09</chemicalAddictionChance>
    <apparelMoney>
      <min>10</min>
      <max>500</max>
    </apparelMoney>
	<apparelTags>
        <li>Neolithic</li>
		<li>FrogmanWear</li>
		<li>RWPGentlemanWear</li> <!-- Michelin J. Frog -->
    </apparelTags>
	<weaponMoney>
         <min>90</min>
         <max>150</max>
    </weaponMoney>
    <backstoryCryptosleepCommonality>0</backstoryCryptosleepCommonality>
    <techHediffsMoney>
      <min>50</min>
      <max>50</max>
    </techHediffsMoney>
    <techHediffsTags>
      <li>Poor</li>
    </techHediffsTags>
    <techHediffsChance>0.02</techHediffsChance>
	<weaponTags>
		<li>Neolithic</li>
		<li>NeolithicMeleeDecent</li>
		<li>NeolithicRangedDecent</li>
		<li>MedievalMeleeDecent</li>
    </weaponTags>
    <initialWillRange>1~4</initialWillRange>
    <initialResistanceRange>5~20</initialResistanceRange>
  </PawnKindDef>
  
  <PawnKindDef ParentName="BasePlayerFrogPersonPawnKind">
    <defName>FrogPersonHunter</defName>
    <label>frogman hunter</label>
    <combatPower>45</combatPower>
    <defaultFactionType>FrogTribes</defaultFactionType>
    <chemicalAddictionChance>0.01</chemicalAddictionChance>
    <apparelMoney>
      <min>40</min>
      <max>300</max>
    </apparelMoney>
	<apparelTags>
        <li>Neolithic</li>
		<li>FrogmanWear</li>
		<li>RWPGentlemanWear</li> <!-- Michelin J. Frog -->
    </apparelTags>
	<weaponMoney>
         <min>50</min>
         <max>300</max>
    </weaponMoney>
    <backstoryCryptosleepCommonality>0</backstoryCryptosleepCommonality>
    <techHediffsMoney>
      <min>50</min>
      <max>50</max>
    </techHediffsMoney>
    <techHediffsTags>
      <li>Poor</li>
    </techHediffsTags>
    <techHediffsChance>0.02</techHediffsChance>
	<weaponTags>
		<li>FrogmanRanged</li>
    </weaponTags>
    <initialWillRange>1~4</initialWillRange>
    <initialResistanceRange>5~20</initialResistanceRange>
  </PawnKindDef>
  
    <PawnKindDef ParentName="BasePlayerFrogPersonPawnKind">
    <defName>FrogPersonWarrior</defName>
    <label>frog warrior</label>
    <combatPower>45</combatPower>
    <defaultFactionType>FrogTribes</defaultFactionType>
    <chemicalAddictionChance>0.01</chemicalAddictionChance>
    <apparelMoney>
      <min>40</min>
      <max>300</max>
    </apparelMoney>
	<apparelTags>
        <li>Neolithic</li>
		<li>FrogmanWear</li>
		<li>RWPGentlemanWear</li> <!-- Michelin J. Frog -->
    </apparelTags>
	<weaponMoney>
         <min>100</min>
         <max>300</max>
    </weaponMoney>
    <backstoryCryptosleepCommonality>0</backstoryCryptosleepCommonality>
    <techHediffsMoney>
      <min>50</min>
      <max>50</max>
    </techHediffsMoney>
    <techHediffsTags>
      <li>Poor</li>
    </techHediffsTags>
    <techHediffsChance>0.02</techHediffsChance>
	<weaponTags>
		<li>FrogmanMelee</li>
    </weaponTags>
    <initialWillRange>1~4</initialWillRange>
    <initialResistanceRange>5~20</initialResistanceRange>
  </PawnKindDef>
  
  <PawnKindDef ParentName="BasePlayerFrogPersonPawnKind">
    <defName>FrogPersonTrader</defName>
    <label>frog merchant</label>
    <trader>true</trader>
	<combatPower>60</combatPower>
	<minGenerationAge>24</minGenerationAge> <!-- Prevents bug when Children are allowed to spawn in V1.3 via Mods causing the trade caravan to pump out massive errors -->
    <defaultFactionType>FrogTribes</defaultFactionType>
    <chemicalAddictionChance>0.01</chemicalAddictionChance>
    <apparelMoney>
      <min>150</min>
      <max>300</max>
    </apparelMoney>
	<apparelTags>
        <li>Neolithic</li>
		<li>FrogmanWear</li>
		<li>RWPGentlemanWear</li> <!-- Michelin J. Frog -->
    </apparelTags>
    <weaponMoney>
         <min>200</min>
         <max>800</max>
    </weaponMoney>
    <backstoryCryptosleepCommonality>0</backstoryCryptosleepCommonality>
    <techHediffsMoney>
      <min>50</min>
      <max>50</max>
    </techHediffsMoney>
    <techHediffsTags>
      <li>Poor</li>
    </techHediffsTags>
    <techHediffsChance>0.02</techHediffsChance>
	<weaponTags>
		<li>FrogmanMelee</li>
        <li>FrogmanRanged</li>
    </weaponTags>
    <initialWillRange>1~4</initialWillRange>
    <initialResistanceRange>5~20</initialResistanceRange>
  </PawnKindDef>
  
  <PawnKindDef ParentName="BasePlayerFrogPersonPawnKind">
    <defName>FrogPersonChief</defName>
    <label>chief frogman</label>
	<combatPower>60</combatPower>
    <defaultFactionType>FrogTribes</defaultFactionType>
    <factionLeader>true</factionLeader>
    <chemicalAddictionChance>0.01</chemicalAddictionChance>
	<minGenerationAge>24</minGenerationAge> <!-- Prevents bug when Children are allowed to spawn in V1.3 via Mods causing the trade caravan to pump out massive errors -->
    <apparelTags>
      <li>Neolithic</li>
	  <li>FrogmanWear</li>
	  <li>RWPGentlemanWear</li> <!-- Michelin J. Frog -->
	  <li>Royal</li>
    </apparelTags>
    <apparelMoney>
      <min>300</min>
      <max>1000</max>
    </apparelMoney>
	<weaponMoney>
         <min>480</min>
         <max>500</max>
    </weaponMoney>
    <backstoryCryptosleepCommonality>0</backstoryCryptosleepCommonality>
    <techHediffsMoney>
      <min>50</min>
      <max>50</max>
    </techHediffsMoney>
    <techHediffsTags>
      <li>Poor</li>
    </techHediffsTags>
    <techHediffsChance>0.02</techHediffsChance>
	<weaponTags>	
        <li>FrogmanMelee</li>
		<li>FrogmanRanged</li>
		<li>SimpleGun</li>
    </weaponTags>
    <initialWillRange>1~4</initialWillRange>
    <initialResistanceRange>5~30</initialResistanceRange>
  </PawnKindDef>
</Defs>