<?xml version="1.0" encoding="utf-8"?>
<Defs>
  <ThingDef ParentName="TSP_VFEAAF_CarMaster">
    <defName>MMTank_NOBASU</defName>
    <label>wild bus</label>
    <description>A proud field van that went wild after the legendary destruction.\nPeople called hunters repeatedly try to make their own cars, but they have failed except a few.\nIt's not have any weapons, but no human can withstand the accel turn of Van's big body.\nIt is equipped with a very cold metal detector, which in its spare time picks up iron scraps and components.</description>
    <statBases>
      <ComfyTemperatureMin>-100</ComfyTemperatureMin>
      <ComfyTemperatureMax>100</ComfyTemperatureMax>
      <MeatAmount>20</MeatAmount>
      <LeatherAmount>30</LeatherAmount>
      <ArmorRating_Blunt>1</ArmorRating_Blunt>
      <ArmorRating_Sharp>0.40</ArmorRating_Sharp>
      <ArmorRating_Heat>0.1</ArmorRating_Heat>
      <ToxicResistance>1</ToxicResistance>
      <PsychicSensitivity>0.1</PsychicSensitivity>
      <Flammability>10</Flammability>
      <MoveSpeed>5</MoveSpeed>
      <MarketValue>800</MarketValue>
      <Mass>250</Mass>
    </statBases>
    <tools>
      <li>
        <label>accelerated turn</label>
        <capacities>
          <li>Blunt</li>
        </capacities>
        <cooldownTime>5</cooldownTime>
        <power>25</power>
        <linkedBodyPartsGroup>HeadAttackTool</linkedBodyPartsGroup>
        <surpriseAttack>
          <extraMeleeDamages>
            <li>
              <def>Stun</def>
              <amount>50</amount>
            </li>
          </extraMeleeDamages>
        </surpriseAttack>
      </li>
    </tools>
    <race>
      <packAnimal>true</packAnimal>
      <petness>0</petness>
      <baseBodySize>20</baseBodySize>
      <baseHungerRate>0.33</baseHungerRate>
	  <!--
	  <specificMeatDef>ChunkSlagSteel</specificMeatDef>
      <leatherDef>ChunkSlagSteel</leatherDef>
	  -->
      <baseHealthScale>0.078</baseHealthScale>
      <foodType>VegetarianRoughAnimal, Kibble</foodType>
      <gestationPeriodDays>60</gestationPeriodDays>
      <trainability>None</trainability>
      <canBePredatorPrey>true</canBePredatorPrey>
      <wildness>0.3</wildness>
      <hasGenders>false</hasGenders>
      <manhunterOnTameFailChance>1</manhunterOnTameFailChance>
      <manhunterOnDamageChance>1</manhunterOnDamageChance>
      <nuzzleMtbHours>4</nuzzleMtbHours>
      <wildBiomes Inherit="False">
        <SeaIce>0.05</SeaIce>
        <IceSheet>0.05</IceSheet>
        <Tundra>0.05</Tundra>
        <BorealForest>0.05</BorealForest>
        <TemperateForest>0.1</TemperateForest>
        <TropicalRainforest>0.15</TropicalRainforest>
        <AridShrubland>0.05</AridShrubland>
        <Desert>0.05</Desert>
        <ExtremeDesert>0.1</ExtremeDesert>
        <TemperateSwamp>0.05</TemperateSwamp>
        <ColdBog>0.05</ColdBog>
        <TropicalSwamp>0.05</TropicalSwamp>
      </wildBiomes>
      <lifeExpectancy>500</lifeExpectancy>
    </race>
    <tradeTags>
      <li>AnimalCommon</li>
    </tradeTags>
    <comps>
      <li Class="CompProperties_Shearable">
        <woolDef>MM_Namaritake</woolDef>
        <shearIntervalDays>5</shearIntervalDays>
        <woolAmount>15</woolAmount>
      </li>
    </comps>
    <butcherProducts>
      <ChunkSlagSteel>10</ChunkSlagSteel>
      <ComponentIndustrial>3</ComponentIndustrial>
    </butcherProducts>
  </ThingDef>
  
  <PawnKindDef ParentName="AnimalKindBase">
    <defName>MMTank_NOBASU</defName>
    <label>wild bus</label>
    <race>MMTank_NOBASU</race>
    <canArriveManhunter>true</canArriveManhunter>
    <combatPower>500</combatPower>
    <ecoSystemWeight>0</ecoSystemWeight>
    <wildGroupSize>
      <min>1</min>
      <max>2</max>
    </wildGroupSize>
    <minGenerationAge>10</minGenerationAge>
    <maxGenerationAge>200</maxGenerationAge>
    <lifeStages>
      <li>
        <bodyGraphicData>
          <texPath>Things/Pawn/Animal/MMTank_NOBASU</texPath>
          <drawSize>1</drawSize>
        </bodyGraphicData>
      </li>
        <dessicatedBodyGraphicData>
          <texPath>Things/Pawn/Animal/MMTank_NOBASU</texPath>
          <drawSize>1</drawSize>
        </dessicatedBodyGraphicData>
      <li>
        <bodyGraphicData>
          <texPath>Things/Pawn/Animal/MMTank_NOBASU</texPath>
          <drawSize>1.8</drawSize>
        </bodyGraphicData>
        <dessicatedBodyGraphicData>
          <texPath>Things/Pawn/Animal/MMTank_NOBASU</texPath>
          <drawSize>1.8</drawSize>
        </dessicatedBodyGraphicData>
      </li>
      <li>
        <bodyGraphicData>
          <texPath>Things/Pawn/Animal/MMTank_NOBASU</texPath>
          <drawSize>2</drawSize>
        </bodyGraphicData>
        <dessicatedBodyGraphicData>
          <texPath>Things/Pawn/Animal/MMTank_NOBASU</texPath>
          <drawSize>2</drawSize>
        </dessicatedBodyGraphicData>
      </li>
    </lifeStages>
  </PawnKindDef>
</Defs>